[
    {
        "name": "generateElement",
        "options": [
            "streetname",
            "name",
            "pastDate",
            "referenceDate",
            "companyName",
            "place",
            "city",
            "event",
            "year",
            "car",
            "low_height",
            "high_height",
            "default"
        ]
    },
    {
        "name": "generateGender",
        "options": ["woman", "man"]
    },
    {
        "name": "generateEventName",
        "options": [
            "Concert",
            "Show",
            "Tour",
            "Spectacle",
            "Rave",
            "Experience",
            "Live"
        ]
    },
    {
        "name": "generateRanking",
        "options": ["plenty of bills to pay","lots of money"]
    },
    {
        "name": "generateRanking",
        "options": [
            [
                "amber",
                "blue",
                "brown",
                "gray",
                "green",
                "hazel"
            ],
            [
                "red",
                "black",
                "brown",
                "blonde",
                "white"
            ]
        ]
    },
    {
        "name": "generateMembership",
        "options": [
            [
                "active",
                "inactive",
                "gold",
                "platinum"
            ]
        ]
    }
]